{
  "item": [
    {
      "id": 1,
      "name": "Chuuuttt!!!",
      "artist": "Jef Aérosol",
      "date": 2012,
      "image": "https://www.kazoart.com/blog/wp-content/uploads/2018/02/lv_90e9c7481775f11179dab05e50af4d226fda4fa6.jpg",
      "localisation": "Paris",
      "note": 4
    },
    {
      "id": 2,
      "name": "El Nestornauta",
      "artist": "graffitimundo",
      "date": 2010,
      "image": "https://graffitimundo.com/wp-content/uploads/2011/01/graffitti-de-el-eternauta.jpg",
      "localisation": "Buenos Aires",
      "note": 2
    }
  ]
}